gudb/__init__.py
gudb/config.py
gudb/exceptions.py
gudb/core/guardian.py
gudb/core/interceptor.py
gudb/core/redactor.py
gudb/middlewares/fastapi.py
gudb/middlewares/flask.py
gudb/providers/base.py
gudb/providers/remote.py
gudb/utils/context.py
gudb/utils/logging.py
gudb-0.1.2.dist-info/METADATA
gudb-0.1.2.dist-info/WHEEL
gudb-0.1.2.dist-info/licenses/LICENSE
gudb-0.1.2.dist-info/RECORD
