Metadata-Version: 2.4
Name: gudb
Version: 0.1.2
Summary: AI-native database seatbelt that blocks destructive SQL, tracks latency, and ships Gemini-powered remediation guidance.
Project-URL: Repository, https://github.com/lu00009/AI-DB-Sentinel.git
Project-URL: Issues, https://github.com/lu00009/AI-DB-Sentinel/issues
Author-email: Gudb Team <hello@gudb.ai>
License-Expression: MIT
License-File: LICENSE
Keywords: ai,database,gudb,monitoring,safety,sentinel,sql,sre
Classifier: Development Status :: 4 - Beta
Classifier: Intended Audience :: Developers
Classifier: Programming Language :: Python :: 3.9
Classifier: Programming Language :: Python :: 3.10
Classifier: Programming Language :: Python :: 3.11
Classifier: Programming Language :: Python :: 3.12
Classifier: Topic :: Database
Classifier: Topic :: Software Development :: Libraries :: Python Modules
Requires-Python: >=3.9
Requires-Dist: psycopg2-binary>=2.9.0
Requires-Dist: pydantic-settings>=2.0.0
Requires-Dist: pydantic>=2.0.0
Requires-Dist: python-dotenv>=1.0.0
Requires-Dist: requests>=2.31.0
Requires-Dist: sqlparse>=0.4.4
Provides-Extra: dev
Requires-Dist: black; extra == 'dev'
Requires-Dist: build; extra == 'dev'
Requires-Dist: httpx>=0.24.0; extra == 'dev'
Requires-Dist: isort; extra == 'dev'
Requires-Dist: pytest-asyncio>=0.21.0; extra == 'dev'
Requires-Dist: pytest>=7.0.0; extra == 'dev'
Requires-Dist: twine; extra == 'dev'
Provides-Extra: fastapi
Requires-Dist: fastapi>=0.100.0; extra == 'fastapi'
Provides-Extra: flask
Requires-Dist: flask>=2.0.0; extra == 'flask'
